<PAMDataset>
  <Metadata domain="IMAGE_STRUCTURE">
    <MDI key="COMPRESSION">JPEG</MDI>
    <MDI key="INTERLEAVE">PIXEL</MDI>
    <MDI key="SOURCE_COLOR_SPACE">YCbCr</MDI>
  </Metadata>
  <PAMRasterBand band="1">
    <Histograms>
      <HistItem>
        <HistMin>-0.5</HistMin>
        <HistMax>252.5</HistMax>
        <BucketCount>253</BucketCount>
        <IncludeOutOfRange>1</IncludeOutOfRange>
        <Approximate>0</Approximate>
        <HistCounts>0|0|0|0|0|0|0|0|0|0|0|0|0|0|0|0|2|1|8|27|120|372|1117|2624|5705|11145|18981|28904|40627|52360|64041|73746|83340|91235|97461|105152|112630|119107|124659|130264|133401|137039|139194|142624|146700|150165|155512|158752|160845|161504|162722|162676|163735|163514|161952|160799|157027|155503|151925|148508|146682|144084|142639|139476|137097|135031|131779|130005|127013|123626|121095|116824|114507|112249|110170|108868|108355|107661|107592|108993|110747|113244|115463|118795|120744|122930|123582|124308|123848|123982|122578|123178|124890|127419|129100|132613|136141|139106|142806|145072|147932|149506|151023|152109|152337|151831|150786|147389|142394|136905|128655|120669|111202|103068|93718|85633|79677|72633|67547|63179|59328|57168|54875|53045|52562|51836|51522|52368|53169|53107|54358|55976|56980|58512|60073|61537|63945|66312|68974|73576|78491|83768|90103|97147|103646|110067|116822|123126|128833|134291|138035|140356|140066|138839|133478|125313|115642|104463|92075|80595|70894|62080|55837|50386|47713|44820|42762|41277|40262|39769|38066|36975|36036|34677|32698|31204|29187|27322|24759|22131|19798|17302|14926|12448|10480|8574|6846|5473|4306|3355|2507|1840|1437|1071|775|648|532|411|385|365|298|315|254|217|186|174|138|141|111|110|92|70|82|57|53|62|45|30|36|32|23|19|14|29|22|15|29|23|17|26|13|10|28|14|18|20|19|23|11|18|17|13|22|21|22|21|23|23|6|9|4|1|1</HistCounts>
      </HistItem>
    </Histograms>
    <Metadata domain="IMAGE_STRUCTURE">
      <MDI key="COMPRESSION">JPEG</MDI>
    </Metadata>
    <Metadata>
      <MDI key="STATISTICS_COVARIANCES">1670.461675692488,1181.95595048241,915.9047561671481</MDI>
      <MDI key="STATISTICS_EXCLUDEDVALUES"></MDI>
      <MDI key="STATISTICS_MAXIMUM">252</MDI>
      <MDI key="STATISTICS_MEAN">93.647097624978</MDI>
      <MDI key="STATISTICS_MEDIAN">90.000000</MDI>
      <MDI key="STATISTICS_MINIMUM">16</MDI>
      <MDI key="STATISTICS_SKIPFACTORX">1</MDI>
      <MDI key="STATISTICS_SKIPFACTORY">1</MDI>
      <MDI key="STATISTICS_STDDEV">40.871281796544</MDI>
    </Metadata>
  </PAMRasterBand>
  <PAMRasterBand band="2">
    <Histograms>
      <HistItem>
        <HistMin>-0.5</HistMin>
        <HistMax>239.5</HistMax>
        <BucketCount>240</BucketCount>
        <IncludeOutOfRange>1</IncludeOutOfRange>
        <Approximate>0</Approximate>
        <HistCounts>0|0|0|0|0|0|0|0|0|0|0|0|0|0|0|0|0|0|0|0|0|0|0|0|0|0|0|0|0|0|0|3|11|51|256|854|2393|5804|11778|20829|32297|45104|57930|69890|80883|90537|99490|109212|119079|128821|137204|146760|155384|162357|166610|169607|170400|170768|171921|173053|174759|174578|172641|170140|167425|165259|162908|161136|159684|158495|156299|153899|152604|149579|148125|145394|144044|141024|139395|136109|133415|130249|127627|126498|124259|122197|122248|122184|123556|125209|128162|132444|138482|145283|152460|160193|170022|178652|185743|193036|197969|202452|205578|209400|214756|218418|220817|224356|226227|222765|218162|210629|199276|189878|177358|165443|155007|146084|138330|133842|130407|128809|129307|131360|135635|140101|145768|150569|156031|160665|163014|165556|165207|162339|155563|145382|133563|119190|104070|90405|77727|68047|60282|54814|50411|47351|45103|43291|40868|38805|37303|34689|32184|29658|27506|24051|21127|18467|15628|13218|10905|8799|7289|5723|4471|3487|2707|2073|1528|1161|875|735|613|496|449|335|310|279|234|216|179|142|152|118|117|96|78|95|80|53|69|57|50|54|42|41|34|36|36|28|28|29|32|27|15|24|23|24|28|20|33|30|24|32|23|26|30|20|23|19|26|19|22|19|26|22|21|21|19|22|26|22|21|15|12|7|2|2|3|1</HistCounts>
      </HistItem>
    </Histograms>
    <Metadata domain="IMAGE_STRUCTURE">
      <MDI key="COMPRESSION">JPEG</MDI>
    </Metadata>
    <Metadata>
      <MDI key="STATISTICS_COVARIANCES">1181.95595048241,866.9749918968863,651.5639192141952</MDI>
      <MDI key="STATISTICS_EXCLUDEDVALUES"></MDI>
      <MDI key="STATISTICS_MAXIMUM">239</MDI>
      <MDI key="STATISTICS_MEAN">94.433492187511</MDI>
      <MDI key="STATISTICS_MEDIAN">97.000000</MDI>
      <MDI key="STATISTICS_MINIMUM">31</MDI>
      <MDI key="STATISTICS_SKIPFACTORX">1</MDI>
      <MDI key="STATISTICS_SKIPFACTORY">1</MDI>
      <MDI key="STATISTICS_STDDEV">29.444439065754</MDI>
    </Metadata>
  </PAMRasterBand>
  <PAMRasterBand band="3">
    <Histograms>
      <HistItem>
        <HistMin>-0.5</HistMin>
        <HistMax>239.5</HistMax>
        <BucketCount>240</BucketCount>
        <IncludeOutOfRange>1</IncludeOutOfRange>
        <Approximate>0</Approximate>
        <HistCounts>0|0|0|0|0|0|0|0|0|0|0|0|0|0|0|0|0|0|0|0|0|0|0|0|0|0|0|0|0|3|3|3|16|24|50|92|191|378|660|1227|2223|3614|5997|9540|15268|23199|34742|49580|69001|92938|119695|146629|171218|191877|206083|213874|220041|225586|231564|239888|248483|256338|263365|267402|269764|270526|270408|271468|272134|272878|273938|272637|270648|266807|266020|265518|266595|270047|272386|275470|276703|276436|275644|274351|271345|269655|266027|261173|253220|243838|232686|217011|200835|182530|165042|147943|133852|121605|112753|105247|99723|95675|93936|92908|92850|92963|95298|97669|100836|105933|112325|118966|128036|136753|146103|155152|163200|169782|174044|174427|171094|164452|153192|138835|123067|109060|94974|82849|72826|64997|58793|53064|48509|43942|39313|35909|30570|26503|22818|19078|15486|12374|10103|7837|5995|4481|3419|2646|1957|1455|1182|912|708|624|496|395|298|273|250|212|187|156|139|118|116|81|84|68|64|63|58|51|59|40|56|48|47|41|38|40|27|28|32|24|33|26|24|21|28|25|28|18|29|33|34|33|25|25|23|24|20|21|30|15|22|28|19|25|18|21|23|27|26|16|26|20|12|12|10|5|5|5|3|2|3|3|3|4|2|3|5|3|5|1|1|1|1|0|0|1</HistCounts>
      </HistItem>
    </Histograms>
    <Metadata domain="IMAGE_STRUCTURE">
      <MDI key="COMPRESSION">JPEG</MDI>
    </Metadata>
    <Metadata>
      <MDI key="STATISTICS_COVARIANCES">915.9047561671481,651.5639192141952,529.5654793577904</MDI>
      <MDI key="STATISTICS_EXCLUDEDVALUES"></MDI>
      <MDI key="STATISTICS_MAXIMUM">239</MDI>
      <MDI key="STATISTICS_MEAN">84.402493000007</MDI>
      <MDI key="STATISTICS_MEDIAN">81.000000</MDI>
      <MDI key="STATISTICS_MINIMUM">29</MDI>
      <MDI key="STATISTICS_SKIPFACTORX">1</MDI>
      <MDI key="STATISTICS_SKIPFACTORY">1</MDI>
      <MDI key="STATISTICS_STDDEV">23.012289746085</MDI>
    </Metadata>
  </PAMRasterBand>
</PAMDataset>
